{
  "Icon": "Icons/ItemsGenerated/HytaleIndustries_PoweredFurnace.png",
  "TranslationProperties": {
    "Name": "16k Storage Disk",
    "Description": "Holds up to 16384 items when inserted into an ES Disk Housing."
  },
  "Model": "Items/HytaleIndustries_ESDisk_16k/HytaleIndustries_ESDisk_16k.blockymodel",
  "Texture": "Items/HytaleIndustries_ESDisk_16k/HytaleIndustries_ESDisk_16k.png",
  "MaxStack": 1,
  "Recipe": {
    "OutputQuantity": 1,
    "PrimaryOutput": { "ItemId": "HytaleIndustries_ES_16kDisk", "Quantity": 1 },
    "BenchRequirement": [{ "Id": "Machinists_Bench", "Type": "Crafting", "Categories": ["Machinists_Storage"] }],
    "Input": [
      { "ItemId": "HytaleIndustries_ES_4kDisk", "Quantity": 1 },
      { "ItemId": "HytaleIndustries_ESCircuit", "Quantity": 4 },
      { "ItemId": "Ingredient_Bar_Gold", "Quantity": 2 }
    ]
  }
}
